pydantable/__init__.py
pydantable/base.py
pydantable/csv.py
pydantable/edit_model.py
pydantable/errors.py
pydantable/strict_table.py
pydantable/table.py
pydantable/validate.py
pydantable-0.3.1.dist-info/LICENSE.md
pydantable-0.3.1.dist-info/METADATA
pydantable-0.3.1.dist-info/WHEEL
pydantable-0.3.1.dist-info/top_level.txt
pydantable-0.3.1.dist-info/RECORD
